zoho_crm_mcp/__init__.py
mseep_zoho_crm_mcp_server-0.1.1.dist-info/METADATA
mseep_zoho_crm_mcp_server-0.1.1.dist-info/WHEEL
mseep_zoho_crm_mcp_server-0.1.1.dist-info/entry_points.txt
mseep_zoho_crm_mcp_server-0.1.1.dist-info/top_level.txt
mseep_zoho_crm_mcp_server-0.1.1.dist-info/RECORD
