Metadata-Version: 2.4
Name: mseep-zoho-crm-mcp-server
Version: 0.1.1
Summary: MCP server for Zoho CRM API integration
Author-email: mseep <support@skydeck.ai>
Requires-Python: >=3.8
Requires-Dist: httpx>=0.24.0
Requires-Dist: pydantic>=2.0
Requires-Dist: pydantic-settings>=2.0
Requires-Dist: python-dotenv>=1.0.0
Provides-Extra: dev
Requires-Dist: pytest>=7.0; extra == "dev"
Requires-Dist: pytest-asyncio>=0.21.0; extra == "dev"
Requires-Dist: pytest-cov>=4.0; extra == "dev"
Requires-Dist: ruff>=0.1.0; extra == "dev"
